vcdiff/__init__.py
vcdiff/client.py
vcdiff_py-2.1.0.dist-info/licenses/LICENSE
vcdiff_py-2.1.0.dist-info/METADATA
vcdiff_py-2.1.0.dist-info/WHEEL
vcdiff_py-2.1.0.dist-info/entry_points.txt
vcdiff_py-2.1.0.dist-info/top_level.txt
vcdiff_py-2.1.0.dist-info/RECORD
